[
    {
        "searchInput": "G",
        "dateFrom": "2022-08-02",
        "dateTo": "2022-08-16",
        "company": "Genpact Ltd",
        "stockPrice": [
            {
                "close": "47.66",
                "open": "47.89",
                "timestamp": "2022-08-02"
            },
            {
                "close": "48.35",
                "open": "47.86",
                "timestamp": "2022-08-03"
            },
            {
                "close": "48.41",
                "open": "48.53",
                "timestamp": "2022-08-04"
            },
            {
                "close": "46.92",
                "open": "47.71",
                "timestamp": "2022-08-05"
            },
            {
                "close": "46.62",
                "open": "47.34",
                "timestamp": "2022-08-08"
            },
            {
                "close": "47.29",
                "open": "46.47",
                "timestamp": "2022-08-09"
            },
            {
                "close": "47.80",
                "open": "47.99",
                "timestamp": "2022-08-10"
            },
            {
                "close": "48.11",
                "open": "47.82",
                "timestamp": "2022-08-11"
            },
            {
                "close": "48.32",
                "open": "48.09",
                "timestamp": "2022-08-12"
            },
            {
                "close": "48.32",
                "open": "47.84",
                "timestamp": "2022-08-15"
            },
            {
                "close": "48.54",
                "open": "48.09",
                "timestamp": "2022-08-16"
            }
        ]
    },
    {
        "searchInput": "K",
        "dateFrom": "2022-08-02",
        "dateTo": "2022-08-16",
        "company": "Kellogg Co",
        "stockPrice": [
            {
                "close": "73.87",
                "open": "74.90",
                "timestamp": "2022-08-02"
            },
            {
                "close": "73.96",
                "open": "73.50",
                "timestamp": "2022-08-03"
            },
            {
                "close": "73.82",
                "open": "74.85",
                "timestamp": "2022-08-04"
            },
            {
                "close": "75.04",
                "open": "74.21",
                "timestamp": "2022-08-05"
            },
            {
                "close": "74.68",
                "open": "74.80",
                "timestamp": "2022-08-08"
            },
            {
                "close": "75.20",
                "open": "75.00",
                "timestamp": "2022-08-09"
            },
            {
                "close": "75.51",
                "open": "75.25",
                "timestamp": "2022-08-10"
            },
            {
                "close": "75.39",
                "open": "75.40",
                "timestamp": "2022-08-11"
            },
            {
                "close": "75.62",
                "open": "75.44",
                "timestamp": "2022-08-12"
            },
            {
                "close": "75.85",
                "open": "75.67",
                "timestamp": "2022-08-15"
            },
            {
                "close": "75.90",
                "open": "75.60",
                "timestamp": "2022-08-16"
            }
        ]
    },
    {
        "searchInput": "C",
        "dateFrom": "2022-08-02",
        "dateTo": "2022-08-09",
        "company": "Citigroup Inc",
        "stockPrice": [
            {
                "close": "50.75",
                "open": "51.76",
                "timestamp": "2022-08-02"
            },
            {
                "close": "51.61",
                "open": "51.24",
                "timestamp": "2022-08-03"
            },
            {
                "close": "51.26",
                "open": "51.56",
                "timestamp": "2022-08-04"
            },
            {
                "close": "51.66",
                "open": "51.12",
                "timestamp": "2022-08-05"
            },
            {
                "close": "51.47",
                "open": "51.97",
                "timestamp": "2022-08-08"
            },
            {
                "close": "52.09",
                "open": "51.64",
                "timestamp": "2022-08-09"
            }
        ]
    }
]